README.md
setup.py
botoless/__init__.py
botoless/core.py
botoless/util.py
botoless.egg-info/PKG-INFO
botoless.egg-info/SOURCES.txt
botoless.egg-info/dependency_links.txt
botoless.egg-info/entry_points.txt
botoless.egg-info/requires.txt
botoless.egg-info/top_level.txt
botoless/dynamodb/__init__.py
botoless/logging/__init__.py
botoless/logging/cloudwatch_handler.py
botoless/logging/config.py
botoless/s3/__init__.py
botoless/sqs/__init__.py