Metadata-Version: 2.1
Name: botoless
Version: 0.1.0
Summary: A smaller view of boto3 intended for serverless application development
Home-page: https://github.com/beaucronin/botoless
Author: Beau Cronin
Author-email: beau.cronin@gmail.com
License: MIT License
